picklellc/__init__.py
picklellc/picklellc.py
picklellc-0.8.1.dist-info/METADATA
picklellc-0.8.1.dist-info/WHEEL
picklellc-0.8.1.dist-info/top_level.txt
picklellc-0.8.1.dist-info/RECORD
